watchlib/__init__.py
watchlib/analysis/__init__.py
watchlib/analysis/analysis_ecg_utils.py
watchlib/analysis/analysis_utils.py
watchlib/analysis/annoy.py
watchlib/analysis/ecg_analysis.py
watchlib/analysis/health_data_stats.py
watchlib/animation/__init__.py
watchlib/animation/config.py
watchlib/animation/constants.py
watchlib/animation/render.py
watchlib/data_handler/__init__.py
watchlib/data_handler/data_handler.py
watchlib/filtering/__init__.py
watchlib/filtering/filters.py
watchlib/plot/__init__.py
watchlib/plot/distributions.py
watchlib/plot/plot.py
watchlib/utils/__init__.py
watchlib/utils/structs.py
watchlib-0.0.1a2.dist-info/LICENSE
watchlib-0.0.1a2.dist-info/METADATA
watchlib-0.0.1a2.dist-info/WHEEL
watchlib-0.0.1a2.dist-info/top_level.txt
watchlib-0.0.1a2.dist-info/RECORD
