Metadata-Version: 2.1
Name: watchlib
Version: 0.0.1a2
Summary: watchlib is a Python package providing tools for loading, visualizing and analyzing Apple Watch health data.
Home-page: https://github.com/marcjulianschwarz/watchlib
Author: Marc Julian Schwarz
Author-email: info@marc-julian.de
License: UNKNOWN
Project-URL: Bug Tracker, https://github.com/marcjulianschwarz/watchlib/issues
Project-URL: Docs, https://github.com/marcjulianschwarz/watchlib/wiki
Platform: UNKNOWN
Classifier: Programming Language :: Python :: 3
Classifier: License :: OSI Approved :: MIT License
Classifier: Operating System :: OS Independent
Requires-Python: >=3.6
License-File: LICENSE
Requires-Dist: pandas
Requires-Dist: numpy
Requires-Dist: matplotlib
Requires-Dist: seaborn
Requires-Dist: annoy
Requires-Dist: sklearn
